Instruction Decode/instruction_decode.v

module InstructionDecoder (
    input [31:0] instruction,  // 32-bit instruction input
    output wire [6:0] opcode,   // Bits [6:0] - Opcode
    output wire [4:0] rs1,      // Bits [19:15] - Source Register 1
    output wire [4:0] rs2,      // Bits [24:20] - Source Register 2
    output wire [4:0] rd,       // Bits [11:7] - Destination Register
    output wire [2:0] funct3,   // Bits [14:12] - Function code
    output wire [6:0] funct7,   // Bits [31:25] - Function code (R-type)
    output wire [31:0] imm      // Immediate value (for I, S, B, U, J types)
);

reg [6:0] opcode_reg;   
reg [4:0] rs1_reg;     
reg [4:0] rs2_reg;      
reg [4:0] rd_reg;       
reg [2:0] funct3_reg;   
reg [6:0] funct7_reg;   
reg [31:0] imm_reg;     

// Connect internal registers to the output wires
assign opcode = opcode_reg;
assign rs1 = rs1_reg;
assign rs2 = rs2_reg;
assign rd = rd_reg;
assign funct3 = funct3_reg;
assign funct7 = funct7_reg;
assign imm = imm_reg;

always @(*) begin
    // Extract opcode first
    opcode_reg = instruction[6:0];

    // Default values (in case instruction is not recognized)
    rs1_reg = 5'b0;
    rs2_reg = 5'b0;
    rd_reg = 5'b0;
    funct3_reg = 3'b0;
    funct7_reg = 7'b0;
    imm_reg = 32'b0;

    case (opcode_reg)
        // --- R-TYPE (Register-Register Operations) ---
        7'b0110011: begin  // ADD, SUB, AND, OR, XOR, SLL, SRL, etc.
            rd_reg     = instruction[11:7];
            rs1_reg    = instruction[19:15];
            rs2_reg    = instruction[24:20];
            funct3_reg = instruction[14:12];
            funct7_reg = instruction[31:25];
        end

        // --- I-TYPE (Immediate Operations) ---
        7'b0010011,  // Arithmetic Immediate (ADDI, ANDI, ORI, XORI, SLLI, SRLI, SRAI)
        7'b0000011,  // Load Instructions (LW, LH, LB, etc.)
        7'b1100111:  // JALR (Jump and Link Register)
        begin
            rd_reg     = instruction[11:7];
            rs1_reg    = instruction[19:15];
            funct3_reg = instruction[14:12];
            imm_reg    = {{20{instruction[31]}}, instruction[31:20]};  // Sign-extended 12-bit immediate
        end

        // --- S-TYPE (Store Operations) ---
        7'b0100011: begin  // SW, SH, SB
            rs1_reg    = instruction[19:15];
            rs2_reg    = instruction[24:20];
            funct3_reg = instruction[14:12];
            imm_reg    = {{20{instruction[31]}}, instruction[31:25], instruction[11:7]};  // Sign-extended
        end

        // --- B-TYPE (Branch Operations) ---
        7'b1100011: begin  // BEQ, BNE, BLT, BGE, etc.
            rs1_reg    = instruction[19:15];
            rs2_reg    = instruction[24:20];
            funct3_reg = instruction[14:12];
            imm_reg    = {{19{instruction[31]}}, instruction[31], instruction[7], instruction[30:25], instruction[11:8], 1'b0};
        end

        // --- U-TYPE (Upper Immediate Operations) ---
        7'b0110111,  // LUI (Load Upper Immediate)
        7'b0010111:  // AUIPC (Add Upper Immediate to PC)
        begin
            rd_reg  = instruction[11:7];
            imm_reg = {instruction[31:12], 12'b0};  // 20-bit immediate (shifted left)
        end

        // --- J-TYPE (Jump Instructions) ---
        7'b1101111: begin  // JAL (Jump and Link)
            rd_reg  = instruction[11:7];
            imm_reg = {{11{instruction[31]}}, instruction[31], instruction[19:12], instruction[20], instruction[30:21], 1'b0};
        end

        default: begin
            // Do nothing (all fields remain zero)
        end
    endcase
end

endmodule


module RegisterFile (
    input clk,                    // Clock signal
    input reset,                  // Reset signal
    input regWrite,               // Write enable signal
    input [4:0] rs1,              // Source register 1 address
    input [4:0] rs2,              // Source register 2 address
    input [4:0] rd,               // Destination register address
    input [63:0] writeData,       // Data to write into rd
    output wire [63:0] readData1,  // Data output for rs1
    output wire [63:0] readData2   // Data output for rs2
);

    // 32 registers of 64-bit each (RISC-V uses 32 registers)
    reg [63:0] registers [0:31];
    reg [63:0] readData1_reg, readData2_reg;
    
    assign readData1 = readData1_reg;
    assign readData2 = readData2_reg;

    // Reset all registers (only for simulation/testing)
    integer i;
    always @(posedge reset) begin
        for (i = 0; i < 32; i = i + 1)
            registers[i] <= 64'b0; // Reset all registers to 0
    end

    // Register Read (Combinational Logic)
    always @(*) begin
        readData1_reg = (rs1 == 5'b0) ? 64'b0 : registers[rs1]; // x0 register is always 0
        readData2_reg = (rs2 == 5'b0) ? 64'b0 : registers[rs2]; // x0 register is always 0
    end

    // Register Write (Synchronous, on clock edge)
    always @(posedge clk) begin
        if (regWrite && rd != 5'b0)  // Prevent writing to x0 (zero register)
            registers[rd] <= writeData;
    end

endmodule

module ImmGen (
    input [31:0] instruction,
    input [6:0] opcode,
    output wire [63:0] imm
);

reg [63:0] imm_reg;
assign imm = imm_reg;

always @(*) begin
    case (opcode)
        // --- I-TYPE (Immediate Operations) ---
        7'b0010011,  // Arithmetic Immediate (ADDI, ANDI, ORI, XORI, SLLI, SRLI, SRAI)
        7'b0000011,  // Load Instructions (LW, LH, LB, etc.)
        7'b1100111:  // JALR (Jump and Link Register)
            imm_reg = {{52{instruction[31]}}, instruction[31:20]};  // Sign-extended 12-bit immediate to 64-bit

        // --- S-TYPE (Store Operations) ---
        7'b0100011:  // SW, SH, SB
            imm_reg = {{52{instruction[31]}}, instruction[31:25], instruction[11:7]};  // Sign-extended to 64-bit

        // --- B-TYPE (Branch Operations) ---
        7'b1100011:  // BEQ, BNE, BLT, BGE, etc.
            imm_reg = {{51{instruction[31]}}, instruction[31], instruction[7], instruction[30:25], instruction[11:8], 1'b0};  // Sign-extended to 64-bit

        // --- U-TYPE (Upper Immediate Operations) ---
        7'b0110111,  // LUI (Load Upper Immediate)
        7'b0010111:  // AUIPC (Add Upper Immediate to PC)
            imm_reg = {{32{instruction[31]}}, instruction[31:12], 12'b0};  // 20-bit immediate (shifted left) sign-extended to 64-bit

        // --- J-TYPE (Jump Instructions) ---
        7'b1101111:  // JAL (Jump and Link)
            imm_reg = {{43{instruction[31]}}, instruction[31], instruction[19:12], instruction[20], instruction[30:21], 1'b0};  // Sign-extended to 64-bit

        default:
            imm_reg = 64'b0;  // Default to zero if opcode is not recognized
    endcase
end

endmodule

module ControlUnit (
    input [6:0] opcode,       // Instruction opcode
    output wire Branch,        // Branch signal
    output wire MemRead,       // Memory read enable
    output wire MemtoReg,      // Select memory output to register
    output wire [1:0] ALUOp,   // ALU operation
    output wire MemWrite,      // Memory write enable
    output wire ALUSrc,        // ALU source selection
    output wire RegWrite       // Register write enable
);

reg Branch_reg, MemRead_reg, MemtoReg_reg;
reg [1:0] ALUOp_reg;
reg MemWrite_reg, ALUSrc_reg, RegWrite_reg;

// Connect internal registers to the output wires
assign Branch = Branch_reg;
assign MemRead = MemRead_reg;
assign MemtoReg = MemtoReg_reg;
assign ALUOp = ALUOp_reg;
assign MemWrite = MemWrite_reg;
assign ALUSrc = ALUSrc_reg;
assign RegWrite = RegWrite_reg;

always @(*) begin
    // Default control signals
    Branch_reg   = 0;
    MemRead_reg  = 0;
    MemtoReg_reg = 0;
    ALUOp_reg    = 2'b00;
    MemWrite_reg = 0;
    ALUSrc_reg   = 0;
    RegWrite_reg = 0;
    
    case (opcode)
        7'b0110011: begin // R-type (ADD, SUB, AND, OR, XOR, etc.)
            RegWrite_reg = 1;
            ALUOp_reg    = 2'b10;
        end
        
        7'b0010011, // I-type (ADDI, ANDI, ORI, XORI, SLLI, SRLI, SRAI)
        7'b0000011: begin // Load (LW, LH, LB)
            RegWrite_reg = 1;
            ALUSrc_reg   = 1;
            MemRead_reg  = (opcode == 7'b0000011) ? 1 : 0;
            MemtoReg_reg = (opcode == 7'b0000011) ? 1 : 0;
            ALUOp_reg    = 2'b00;
        end
        
        7'b0100011: begin // S-type (Store: SW, SH, SB)
            MemWrite_reg = 1;
            ALUSrc_reg   = 1;
            ALUOp_reg    = 2'b00;
        end
        
        7'b1100011: begin // B-type (Branch: BEQ, BNE, etc.)
            Branch_reg   = 1;
            ALUOp_reg    = 2'b01;
        end
        
        7'b1101111, // J-type (JAL: Jump and Link)
        7'b1100111: begin // JALR (Jump and Link Register)
            RegWrite_reg = 1;
            ALUSrc_reg   = 1;
            ALUOp_reg    = 2'b00;
        end
    
        7'b0110111, // U-type (LUI: Load Upper Immediate)
        7'b0010111: begin // AUIPC (Add Upper Immediate to PC)
            RegWrite_reg = 1;
            ALUSrc_reg   = 1;
            ALUOp_reg    = 2'b00;
        end
        
        default: begin
            // Default: Keep all signals low
        end
    endcase
end

endmodule

Instruction Decode/test.v

`include "instruction_decode.v"

module testbench_risc_v;
    // Test signals
    reg [31:0] instruction;
    wire [6:0] opcode;
    wire [4:0] rs1;
    wire [4:0] rs2;
    wire [4:0] rd;
    wire [2:0] funct3;
    wire [6:0] funct7;
    wire [31:0] imm;
    
    // Control signals for verification
    wire Branch, MemRead, MemtoReg, MemWrite, ALUSrc, RegWrite;
    wire [1:0] ALUOp;
    
    // Module instantiations
    InstructionDecoder id (
        .instruction(instruction),
        .opcode(opcode),
        .rs1(rs1),
        .rs2(rs2),
        .rd(rd),
        .funct3(funct3),
        .funct7(funct7),
        .imm(imm)
    );
    
    ControlUnit cu (
        .opcode(opcode),
        .Branch(Branch),
        .MemRead(MemRead),
        .MemtoReg(MemtoReg),
        .ALUOp(ALUOp),
        .MemWrite(MemWrite),
        .ALUSrc(ALUSrc),
        .RegWrite(RegWrite)
    );
    
    // Task to display instruction details
    task display_instruction;
        input [31:0] inst;
        input [255:0] inst_name;
        begin
            $display("==================================================================");
            $display("Testing instruction: %s (0x%h)", inst_name, inst);
            $display("------------------------------------------------------------------");
            $display("Decoded fields:");
            $display("  opcode = 0b%b (0x%h)", opcode, opcode);
            $display("  rd     = %d (x%d)", rd, rd);
            $display("  rs1    = %d (x%d)", rs1, rs1);
            $display("  rs2    = %d (x%d)", rs2, rs2);
            $display("  funct3 = 0b%b", funct3);
            $display("  funct7 = 0b%b", funct7);
            $display("  imm    = 0x%h", imm);
            $display("Control signals:");
            $display("  RegWrite = %b", RegWrite);
            $display("  ALUSrc   = %b", ALUSrc);
            $display("  MemWrite = %b", MemWrite);
            $display("  MemRead  = %b", MemRead);
            $display("  Branch   = %b", Branch);
            $display("  MemtoReg = %b", MemtoReg);
            $display("  ALUOp    = %b", ALUOp);
            $display("==================================================================\n");
        end
    endtask
    
    initial begin
        // Wait to stabilize signals
        #5;
        
        // 1. ADD instruction: add x5, x6, x7
        // Format: funct7[31:25] rs2[24:20] rs1[19:15] funct3[14:12] rd[11:7] opcode[6:0]
        // Encoding: 0000000 00111 00110 000 00101 0110011
        instruction = 32'h00730233;  // add x4, x6, x7
        #10;
        display_instruction(instruction, "ADD x4, x6, x7");
        
        // 2. SUB instruction: sub x9, x10, x11
        // SUB uses funct7=0100000 to differentiate from ADD
        // Encoding: 0100000 01011 01010 000 01001 0110011
        instruction = 32'h40b504b3;  // sub x9, x10, x11
        #10;
        display_instruction(instruction, "SUB x9, x10, x11");
        
        // 3. AND instruction: and x12, x13, x14
        // AND uses funct3=111
        // Encoding: 0000000 01110 01101 111 01100 0110011
        instruction = 32'h00e6f633;  // and x12, x13, x14
        #10;
        display_instruction(instruction, "AND x12, x13, x14");
        
        // 4. OR instruction: or x15, x16, x17
        // OR uses funct3=110
        // Encoding: 0000000 10001 10000 110 01111 0110011
        instruction = 32'h011807b3;  // or x15, x16, x17
        #10;
        display_instruction(instruction, "OR x15, x16, x17");
        
        // 5. LD instruction: ld x8, 16(x20)
        // Format: imm[11:0] rs1[19:15] funct3[14:12] rd[11:7] opcode[6:0]
        // Encoding: 000000010000 10100 011 01000 0000011
        instruction = 32'h010a3403;  // ld x8, 16(x20)
        #10;
        display_instruction(instruction, "LD x8, 16(x20)");
        
        // 6. SD instruction: sd x22, -24(x23)
        // Format: imm[11:5] rs2[24:20] rs1[19:15] funct3[14:12] imm[4:0] opcode[6:0]
        // Encoding: 1111111 10110 10111 011 11000 0100011
        instruction = 32'hfe6b8c23;  // sd x22, -24(x23)
        #10;
        display_instruction(instruction, "SD x22, -24(x23)");
        
        // 7. BEQ instruction: beq x24, x25, offset(16)
        // Format: imm[12|10:5] rs2[24:20] rs1[19:15] funct3[14:12] imm[4:1|11] opcode[6:0]
        // Encoding: 0000000 11001 11000 000 10000 1100011
        instruction = 32'h019c0863;  // beq x24, x25, 16
        #10;
        display_instruction(instruction, "BEQ x24, x25, 16");
        
        $finish;
    end
    
    // Additional logging for waveform analysis
    initial begin
        $dumpfile("risc_v_testbench.vcd");
        $dumpvars(0, testbench_risc_v);
    end
endmodule

Instruction Decode/risc_v_testbench.vcd
$date
	Sun Mar  2 16:33:01 2025
$end
$version
	Icarus Verilog
$end
$timescale
	1s
$end
$scope module testbench_risc_v $end
$var wire 5 ! rs2 [4:0] $end
$var wire 5 " rs1 [4:0] $end
$var wire 5 # rd [4:0] $end
$var wire 7 $ opcode [6:0] $end
$var wire 32 % imm [31:0] $end
$var wire 7 & funct7 [6:0] $end
$var wire 3 ' funct3 [2:0] $end
$var wire 1 ( RegWrite $end
$var wire 1 ) MemtoReg $end
$var wire 1 * MemWrite $end
$var wire 1 + MemRead $end
$var wire 1 , Branch $end
$var wire 1 - ALUSrc $end
$var wire 2 . ALUOp [1:0] $end
$var reg 32 / instruction [31:0] $end
$scope module cu $end
$var wire 2 0 ALUOp [1:0] $end
$var wire 1 - ALUSrc $end
$var wire 1 , Branch $end
$var wire 1 + MemRead $end
$var wire 1 * MemWrite $end
$var wire 1 ) MemtoReg $end
$var wire 1 ( RegWrite $end
$var wire 7 1 opcode [6:0] $end
$var reg 2 2 ALUOp_reg [1:0] $end
$var reg 1 3 ALUSrc_reg $end
$var reg 1 4 Branch_reg $end
$var reg 1 5 MemRead_reg $end
$var reg 1 6 MemWrite_reg $end
$var reg 1 7 MemtoReg_reg $end
$var reg 1 8 RegWrite_reg $end
$upscope $end
$scope module id $end
$var wire 3 9 funct3 [2:0] $end
$var wire 7 : funct7 [6:0] $end
$var wire 32 ; imm [31:0] $end
$var wire 32 < instruction [31:0] $end
$var wire 7 = opcode [6:0] $end
$var wire 5 > rd [4:0] $end
$var wire 5 ? rs1 [4:0] $end
$var wire 5 @ rs2 [4:0] $end
$var reg 3 A funct3_reg [2:0] $end
$var reg 7 B funct7_reg [6:0] $end
$var reg 32 C imm_reg [31:0] $end
$var reg 7 D opcode_reg [6:0] $end
$var reg 5 E rd_reg [4:0] $end
$var reg 5 F rs1_reg [4:0] $end
$var reg 5 G rs2_reg [4:0] $end
$upscope $end
$scope task display_instruction $end
$var reg 32 H inst [31:0] $end
$var reg 256 I inst_name [255:0] $end
$upscope $end
$upscope $end
$enddefinitions $end
#0
$dumpvars
bx I
bx H
bx G
bx F
bx E
bx D
bx C
bx B
bx A
bx @
bx ?
bx >
bx =
bx <
bx ;
bx :
bx 9
x8
x7
x6
x5
x4
x3
bx 2
bx 1
bx 0
bx /
bx .
x-
x,
x+
x*
x)
x(
bx '
bx &
bx %
bx $
bx #
bx "
bx !
$end
#5
1(
18
0-
03
0*
06
b10 .
b10 0
b10 2
0)
07
0+
05
0,
04
b0 %
b0 ;
b0 C
b0 &
b0 :
b0 B
b0 '
b0 9
b0 A
b100 #
b100 >
b100 E
b111 !
b111 @
b111 G
b110 "
b110 ?
b110 F
b110011 $
b110011 1
b110011 =
b110011 D
b11100110000001000110011 /
b11100110000001000110011 <
#15
b100000 &
b100000 :
b100000 B
b1001 #
b1001 >
b1001 E
b1011 !
b1011 @
b1011 G
b1010 "
b1010 ?
b1010 F
b1000000101101010000010010110011 /
b1000000101101010000010010110011 <
b100000101000100010001000010000001111000001101000010110000100000011110000011011000101100001000000111100000110111 I
b11100110000001000110011 H
#25
b111 '
b111 9
b111 A
b0 &
b0 :
b0 B
b1100 #
b1100 >
b1100 E
b1110 !
b1110 @
b1110 G
b1101 "
b1101 ?
b1101 F
b111001101111011000110011 /
b111001101111011000110011 <
b1010011010101010100001000100000011110000011100100101100001000000111100000110001001100000010110000100000011110000011000100110001 I
b1000000101101010000010010110011 H
#35
b0 '
b0 9
b0 A
b1111 #
b1111 >
b1111 E
b10001 !
b10001 @
b10001 G
b10000 "
b10000 ?
b10000 F
b1000110000000011110110011 /
b1000110000000011110110011 <
b100000101001110010001000010000001111000001100010011001000101100001000000111100000110001001100110010110000100000011110000011000100110100 I
b111001101111011000110011 H
#45
1)
17
1+
15
1-
13
1(
18
b0 .
b0 0
b0 2
b10000 %
b10000 ;
b10000 C
b11 '
b11 9
b11 A
b1000 #
b1000 >
b1000 E
b0 !
b0 @
b0 G
b10100 "
b10100 ?
b10100 F
b11 $
b11 1
b11 =
b11 D
b1000010100011010000000011 /
b1000010100011010000000011 <
b1001111010100100010000001111000001100010011010100101100001000000111100000110001001101100010110000100000011110000011000100110111 I
b1000110000000011110110011 H
#55
1*
16
0(
08
1-
13
0)
07
0+
05
b110 !
b110 @
b110 G
b11111111111111111111111111111000 %
b11111111111111111111111111111000 ;
b11111111111111111111111111111000 C
b0 '
b0 9
b0 A
b0 #
b0 >
b0 E
b10111 "
b10111 ?
b10111 F
b100011 $
b100011 1
b100011 =
b100011 D
b11111110011010111000110000100011 /
b11111110011010111000110000100011 <
b100110001000100001000000111100000111000001011000010000000110001001101100010100001111000001100100011000000101001 I
b1000010100011010000000011 H
#65
b1 .
b1 0
b1 2
1,
14
0-
03
0*
06
b10000 %
b10000 ;
b10000 C
b11001 !
b11001 @
b11001 G
b11000 "
b11000 ?
b11000 F
b1100011 $
b1100011 1
b1100011 =
b1100011 D
b1100111000000100001100011 /
b1100111000000100001100011 <
b1010011010001000010000001111000001100100011001000101100001000000010110100110010001101000010100001111000001100100011001100101001 I
b11111110011010111000110000100011 H
#75
b1000010010001010101000100100000011110000011001000110100001011000010000001111000001100100011010100101100001000000011000100110110 I
b1100111000000100001100011 H
